uwsgiconf/__init__.py
uwsgiconf/base.py
uwsgiconf/cli.py
uwsgiconf/config.py
uwsgiconf/exceptions.py
uwsgiconf/formatters.py
uwsgiconf/maintenance.py
uwsgiconf/settings.py
uwsgiconf/sysinit.py
uwsgiconf/typehints.py
uwsgiconf/utils.py
uwsgiconf/uwsgi.py
uwsgiconf/uwsgi_stub.py
uwsgiconf/contrib/django/__init__.py
uwsgiconf/contrib/django/uwsgify/__init__.py
uwsgiconf/contrib/django/uwsgify/apps.py
uwsgiconf/contrib/django/uwsgify/cache.py
uwsgiconf/contrib/django/uwsgify/models.py
uwsgiconf/contrib/django/uwsgify/settings.py
uwsgiconf/contrib/django/uwsgify/toolbox.py
uwsgiconf/contrib/django/uwsgify/utils.py
uwsgiconf/contrib/django/uwsgify/uwsgiinit.py
uwsgiconf/contrib/django/uwsgify/admin/__init__.py
uwsgiconf/contrib/django/uwsgify/admin/base.py
uwsgiconf/contrib/django/uwsgify/admin/models.py
uwsgiconf/contrib/django/uwsgify/admin/realms.py
uwsgiconf/contrib/django/uwsgify/admin/task.py
uwsgiconf/contrib/django/uwsgify/locale/ru/LC_MESSAGES/django.mo
uwsgiconf/contrib/django/uwsgify/locale/ru/LC_MESSAGES/django.po
uwsgiconf/contrib/django/uwsgify/management/__init__.py
uwsgiconf/contrib/django/uwsgify/management/commands/__init__.py
uwsgiconf/contrib/django/uwsgify/management/commands/_base.py
uwsgiconf/contrib/django/uwsgify/management/commands/uwsgi_log.py
uwsgiconf/contrib/django/uwsgify/management/commands/uwsgi_reload.py
uwsgiconf/contrib/django/uwsgify/management/commands/uwsgi_run.py
uwsgiconf/contrib/django/uwsgify/management/commands/uwsgi_stats.py
uwsgiconf/contrib/django/uwsgify/management/commands/uwsgi_stop.py
uwsgiconf/contrib/django/uwsgify/management/commands/uwsgi_sysinit.py
uwsgiconf/contrib/django/uwsgify/migrations/0001_initial.py
uwsgiconf/contrib/django/uwsgify/migrations/0002_task_active.py
uwsgiconf/contrib/django/uwsgify/migrations/0003_alter_task_info.py
uwsgiconf/contrib/django/uwsgify/migrations/__init__.py
uwsgiconf/contrib/django/uwsgify/static/uwsgify/403.html
uwsgiconf/contrib/django/uwsgify/static/uwsgify/404.html
uwsgiconf-2.3.0.dist-info/METADATA
uwsgiconf-2.3.0.dist-info/WHEEL
uwsgiconf-2.3.0.dist-info/entry_points.txt
uwsgiconf-2.3.0.dist-info/licenses/LICENSE
uwsgiconf-2.3.0.dist-info/RECORD
