Metadata-Version: 2.4
Name: uwsgiconf
Version: 2.3.0
Summary: Configure uWSGI from your Python code.
Project-URL: Homepage, https://github.com/idlesign/uwsgiconf
Project-URL: Documentation, https://uwsgiconf.readthedocs.io/
Author-email: Igor Starikov <idlesign@yandex.ru>
License-Expression: BSD-3-Clause
License-File: LICENSE
Keywords: configuration,uWSGI
Requires-Python: >=3.10
Provides-Extra: cli
Requires-Dist: click>=2.0.0; extra == 'cli'
